memepay/__init__.py
memepay/client.py
memepay/models.py
memepay/webhook.py
memepay-0.1.5.dist-info/METADATA
memepay-0.1.5.dist-info/WHEEL
memepay-0.1.5.dist-info/top_level.txt
memepay-0.1.5.dist-info/RECORD
