Metadata-Version: 2.4
Name: memepay
Version: 0.1.5
Summary: MemePay Python SDK
Home-page: https://memepay.lol
Author: MemePay
Author-email: support@memepay.lol
Project-URL: Documentation, https://memepay.lol/docs
Classifier: Programming Language :: Python :: 3
Classifier: License :: OSI Approved :: MIT License
Classifier: Operating System :: OS Independent
Requires-Python: >=3.6
Requires-Dist: requests
Requires-Dist: pydantic
Dynamic: author
Dynamic: author-email
Dynamic: classifier
Dynamic: description
Dynamic: description-content-type
Dynamic: home-page
Dynamic: project-url
Dynamic: requires-dist
Dynamic: requires-python
Dynamic: summary
